{
  "Workflows": [
    {
      "Path": null,
      "SortBy": 0,
      "VariablesSectionElementsOrder": null,
      "ArgumentsSectionElementsOrder": null,
      "ConstantsSectionElementsOrder": [],
      "AddedNamespaces": null
    },
    {
      "Path": "Main.xaml",
      "SortBy": 0,
      "VariablesSectionElementsOrder": [
        "syllabus&Sequence_1",
        "sectionAInput&Sequence_1",
        "sectionBInput&Sequence_1",
        "generatedQuestionPaper&Sequence_1",
        "Output&Sequence_1",
        "pattern&Sequence_1",
        "extra&Sequence_1"
      ],
      "ArgumentsSectionElementsOrder": [],
      "ConstantsSectionElementsOrder": [],
      "AddedNamespaces": null
    }
  ]
}